cyaron/__init__.py
cyaron/compare.py
cyaron/consts.py
cyaron/graders/__init__.py
cyaron/graders/fulltext.py
cyaron/graders/graderregistry.py
cyaron/graders/mismatch.py
cyaron/graders/noipstyle.py
cyaron/graph.py
cyaron/io.py
cyaron/log.py
cyaron/math.py
cyaron/merger.py
cyaron/output_capture.py
cyaron/polygon.py
cyaron/sequence.py
cyaron/string.py
cyaron/tests/__init__.py
cyaron/tests/compare_test.py
cyaron/tests/general_test.py
cyaron/tests/graph_test.py
cyaron/tests/io_test.py
cyaron/tests/polygon_test.py
cyaron/tests/sequence_test.py
cyaron/tests/str_test.py
cyaron/tests/vector_test.py
cyaron/utils.py
cyaron/vector.py
cyaron/visual.py
cyaron-0.7.0.dist-info/LICENSE
cyaron-0.7.0.dist-info/METADATA
cyaron-0.7.0.dist-info/WHEEL
cyaron-0.7.0.dist-info/RECORD
