Metadata-Version: 2.3
Name: cyaron
Version: 0.7.0
Summary: CYaRon: Yet Another Random Olympic-iNformatics test data generator, A library for automatically generating test data for Online Judge, Olympic Informatics or automatic application testing
License: LGPL-3.0
Author: Luogu Development Team
Author-email: k@luogu.org
Requires-Python: >=3.6
Classifier: License :: OSI Approved :: GNU Lesser General Public License v3 (LGPLv3)
Classifier: Programming Language :: Python :: 3
Classifier: Programming Language :: Python :: 3.6
Classifier: Programming Language :: Python :: 3.7
Classifier: Programming Language :: Python :: 3.8
Classifier: Programming Language :: Python :: 3.9
Classifier: Programming Language :: Python :: 3.10
Classifier: Programming Language :: Python :: 3.11
Classifier: Programming Language :: Python :: 3.12
Classifier: Programming Language :: Python :: 3.13
Requires-Dist: colorful (>=0.5.6,<0.6.0)
Requires-Dist: xeger (>=0.4.0,<0.5.0)
Project-URL: Bug Tracker, https://github.com/luogu-dev/cyaron/issues
Project-URL: Homepage, https://github.com/luogu-dev/cyaron
